_motion_3000.pyd
DMC3000/LTDMC.dll
DMC3000/LTDMC.h
DMC3000/LTDMC.lib
DMC3000/PVT.dll
DMC3000/__init__.py
DMC3000/_motion_3000.pyd
DMC3000/motion_3000.h
DMC3000/motion_3000.i
DMC3000/motion_3000.py
DMC3000-0.1.dist-info/LICENSE
DMC3000-0.1.dist-info/METADATA
DMC3000-0.1.dist-info/WHEEL
DMC3000-0.1.dist-info/top_level.txt
DMC3000-0.1.dist-info/RECORD
