Metadata-Version: 2.1
Name: DMC3000
Version: 0.1
Summary: Python module for DMC3000
Home-page: UNKNOWN
Author: SF Zhou, WingC
Author-email: 1018957763@qq.com
License: GPL
Platform: UNKNOWN
Classifier: Development Status :: 3 - Alpha
Classifier: Intended Audience :: Developers
Classifier: License :: OSI Approved :: GNU Affero General Public License v3
Classifier: Programming Language :: Python :: 3
Requires-Python: >=3.4
